[ {
  "team_id" : 220,
  "team_name" : "Real Madrid",
  "lineup" : [ {
    "player_id" : 3990,
    "player_name" : "Jesé Rodríguez Ruiz",
    "player_nickname" : "Jesé",
    "jersey_number" : 20,
    "country" : {
      "id" : 214,
      "name" : "Spain"
    },
    "cards" : [ ],
    "positions" : [ ]
  }, {
    "player_id" : 4926,
    "player_name" : "Francisco Román Alarcón Suárez",
    "player_nickname" : "Isco",
    "jersey_number" : 22,
    "country" : {
      "id" : 214,
      "name" : "Spain"
    },
    "cards" : [ ],
    "positions" : [ {
      "position_id" : 17,
      "position" : "Right Wing",
      "from" : "00:00",
      "to" : "70:04",
      "from_period" : 1,
      "to_period" : 2,
      "start_reason" : "Starting XI",
      "end_reason" : "Tactical Shift"
    }, {
      "position_id" : 21,
      "position" : "Left Wing",
      "from" : "70:04",
      "to" : null,
      "from_period" : 2,
      "to_period" : null,
      "start_reason" : "Tactical Shift",
      "end_reason" : "Final Whistle"
    } ]
  }, {
    "player_id" : 5200,
    "player_name" : "Lucas Vázquez Iglesias",
    "player_nickname" : "Lucas Vázquez",
    "jersey_number" : 18,
    "country" : {
      "id" : 214,
      "name" : "Spain"
    },
    "cards" : [ ],
    "positions" : [ {
      "position_id" : 23,
      "position" : "Center Forward",
      "from" : "61:58",
      "to" : "70:04",
      "from_period" : 2,
      "to_period" : 2,
      "start_reason" : "Substitution - On (Tactical)",
      "end_reason" : "Tactical Shift"
    }, {
      "position_id" : 17,
      "position" : "Right Wing",
      "from" : "70:04",
      "to" : null,
      "from_period" : 2,
      "to_period" : null,
      "start_reason" : "Tactical Shift",
      "end_reason" : "Final Whistle"
    } ]
  }, {
    "player_id" : 5201,
    "player_name" : "Sergio Ramos García",
    "player_nickname" : "Sergio Ramos",
    "jersey_number" : 4,
    "country" : {
      "id" : 214,
      "name" : "Spain"
    },
    "cards" : [ ],
    "positions" : [ {
      "position_id" : 5,
      "position" : "Left Center Back",
      "from" : "00:00",
      "to" : "37:48",
      "from_period" : 1,
      "to_period" : 1,
      "start_reason" : "Starting XI",
      "end_reason" : "Player Off"
    }, {
      "position_id" : 5,
      "position" : "Left Center Back",
      "from" : "38:12",
      "to" : "70:04",
      "from_period" : 1,
      "to_period" : 2,
      "start_reason" : "Player On (Off Camera)",
      "end_reason" : "Tactical Shift"
    }, {
      "position_id" : 3,
      "position" : "Right Center Back",
      "from" : "70:04",
      "to" : "74:09",
      "from_period" : 2,
      "to_period" : 2,
      "start_reason" : "Tactical Shift",
      "end_reason" : "Substitution - Off (Tactical)"
    } ]
  }, {
    "player_id" : 5207,
    "player_name" : "Cristiano Ronaldo dos Santos Aveiro",
    "player_nickname" : "Cristiano Ronaldo",
    "jersey_number" : 7,
    "country" : {
      "id" : 183,
      "name" : "Portugal"
    },
    "cards" : [ ],
    "positions" : [ {
      "position_id" : 21,
      "position" : "Left Wing",
      "from" : "00:00",
      "to" : "70:04",
      "from_period" : 1,
      "to_period" : 2,
      "start_reason" : "Starting XI",
      "end_reason" : "Tactical Shift"
    }, {
      "position_id" : 23,
      "position" : "Center Forward",
      "from" : "70:04",
      "to" : null,
      "from_period" : 2,
      "to_period" : null,
      "start_reason" : "Tactical Shift",
      "end_reason" : "Final Whistle"
    } ]
  }, {
    "player_id" : 5456,
    "player_name" : "Mateo Kovačić",
    "player_nickname" : null,
    "jersey_number" : 16,
    "country" : {
      "id" : 56,
      "name" : "Croatia"
    },
    "cards" : [ {
      "time" : "68:04",
      "card_type" : "Yellow Card",
      "reason" : "Foul Committed",
      "period" : 2
    } ],
    "positions" : [ {
      "position_id" : 11,
      "position" : "Left Defensive Midfield",
      "from" : "55:34",
      "to" : "70:04",
      "from_period" : 2,
      "to_period" : 2,
      "start_reason" : "Substitution - On (Tactical)",
      "end_reason" : "Tactical Shift"
    }, {
      "position_id" : 9,
      "position" : "Right Defensive Midfield",
      "from" : "70:04",
      "to" : null,
      "from_period" : 2,
      "to_period" : null,
      "start_reason" : "Tactical Shift",
      "end_reason" : "Final Whistle"
    } ]
  }, {
    "player_id" : 5463,
    "player_name" : "Luka Modrić",
    "player_nickname" : null,
    "jersey_number" : 19,
    "country" : {
      "id" : 56,
      "name" : "Croatia"
    },
    "cards" : [ ],
    "positions" : [ {
      "position_id" : 11,
      "position" : "Left Defensive Midfield",
      "from" : "00:00",
      "to" : "55:34",
      "from_period" : 1,
      "to_period" : 2,
      "start_reason" : "Starting XI",
      "end_reason" : "Substitution - Off (Tactical)"
    } ]
  }, {
    "player_id" : 5485,
    "player_name" : "Raphaël Varane",
    "player_nickname" : null,
    "jersey_number" : 2,
    "country" : {
      "id" : 78,
      "name" : "France"
    },
    "cards" : [ ],
    "positions" : [ {
      "position_id" : 3,
      "position" : "Right Center Back",
      "from" : "74:09",
      "to" : null,
      "from_period" : 2,
      "to_period" : null,
      "start_reason" : "Substitution - On (Tactical)",
      "end_reason" : "Final Whistle"
    } ]
  }, {
    "player_id" : 5539,
    "player_name" : "Carlos Henrique Casimiro",
    "player_nickname" : "Casemiro",
    "jersey_number" : 14,
    "country" : {
      "id" : 31,
      "name" : "Brazil"
    },
    "cards" : [ ],
    "positions" : [ {
      "position_id" : 9,
      "position" : "Right Defensive Midfield",
      "from" : "00:00",
      "to" : "70:04",
      "from_period" : 1,
      "to_period" : 2,
      "start_reason" : "Starting XI",
      "end_reason" : "Tactical Shift"
    }, {
      "position_id" : 11,
      "position" : "Left Defensive Midfield",
      "from" : "70:04",
      "to" : null,
      "from_period" : 2,
      "to_period" : null,
      "start_reason" : "Tactical Shift",
      "end_reason" : "Final Whistle"
    } ]
  }, {
    "player_id" : 5552,
    "player_name" : "Marcelo Vieira da Silva Júnior",
    "player_nickname" : "Marcelo",
    "jersey_number" : 12,
    "country" : {
      "id" : 31,
      "name" : "Brazil"
    },
    "cards" : [ ],
    "positions" : [ {
      "position_id" : 6,
      "position" : "Left Back",
      "from" : "00:00",
      "to" : null,
      "from_period" : 1,
      "to_period" : null,
      "start_reason" : "Starting XI",
      "end_reason" : "Final Whistle"
    } ]
  }, {
    "player_id" : 5574,
    "player_name" : "Toni Kroos",
    "player_nickname" : null,
    "jersey_number" : 8,
    "country" : {
      "id" : 85,
      "name" : "Germany"
    },
    "cards" : [ ],
    "positions" : [ ]
  }, {
    "player_id" : 5597,
    "player_name" : "Keylor Navas Gamboa",
    "player_nickname" : "Keylor Navas",
    "jersey_number" : 1,
    "country" : {
      "id" : 54,
      "name" : "Costa Rica"
    },
    "cards" : [ ],
    "positions" : [ {
      "position_id" : 1,
      "position" : "Goalkeeper",
      "from" : "00:00",
      "to" : null,
      "from_period" : 1,
      "to_period" : null,
      "start_reason" : "Starting XI",
      "end_reason" : "Final Whistle"
    } ]
  }, {
    "player_id" : 5721,
    "player_name" : "Daniel Carvajal Ramos",
    "player_nickname" : "Daniel Carvajal",
    "jersey_number" : 15,
    "country" : {
      "id" : 214,
      "name" : "Spain"
    },
    "cards" : [ ],
    "positions" : [ {
      "position_id" : 2,
      "position" : "Right Back",
      "from" : "00:00",
      "to" : null,
      "from_period" : 1,
      "to_period" : null,
      "start_reason" : "Starting XI",
      "end_reason" : "Final Whistle"
    } ]
  }, {
    "player_id" : 6399,
    "player_name" : "Gareth Frank Bale",
    "player_nickname" : "Gareth Bale",
    "jersey_number" : 11,
    "country" : {
      "id" : 249,
      "name" : "Wales"
    },
    "cards" : [ ],
    "positions" : [ {
      "position_id" : 19,
      "position" : "Center Attacking Midfield",
      "from" : "00:00",
      "to" : null,
      "from_period" : 1,
      "to_period" : null,
      "start_reason" : "Starting XI",
      "end_reason" : "Final Whistle"
    } ]
  }, {
    "player_id" : 6706,
    "player_name" : "Francisco Casilla Cortés",
    "player_nickname" : "Kiko Casilla",
    "jersey_number" : 13,
    "country" : {
      "id" : 214,
      "name" : "Spain"
    },
    "cards" : [ ],
    "positions" : [ ]
  }, {
    "player_id" : 19677,
    "player_name" : "Karim Benzema",
    "player_nickname" : null,
    "jersey_number" : 9,
    "country" : {
      "id" : 78,
      "name" : "France"
    },
    "cards" : [ {
      "time" : "35:17",
      "card_type" : "Yellow Card",
      "reason" : "Foul Committed",
      "period" : 1
    } ],
    "positions" : [ {
      "position_id" : 23,
      "position" : "Center Forward",
      "from" : "00:00",
      "to" : "61:58",
      "from_period" : 1,
      "to_period" : 2,
      "start_reason" : "Starting XI",
      "end_reason" : "Substitution - Off (Tactical)"
    } ]
  }, {
    "player_id" : 20016,
    "player_name" : "Kléper Laveran Lima Ferreira",
    "player_nickname" : "Pepe",
    "jersey_number" : 3,
    "country" : {
      "id" : 183,
      "name" : "Portugal"
    },
    "cards" : [ ],
    "positions" : [ {
      "position_id" : 3,
      "position" : "Right Center Back",
      "from" : "00:00",
      "to" : "70:04",
      "from_period" : 1,
      "to_period" : 2,
      "start_reason" : "Starting XI",
      "end_reason" : "Tactical Shift"
    }, {
      "position_id" : 5,
      "position" : "Left Center Back",
      "from" : "70:04",
      "to" : null,
      "from_period" : 2,
      "to_period" : null,
      "start_reason" : "Tactical Shift",
      "end_reason" : "Final Whistle"
    } ]
  }, {
    "player_id" : 20215,
    "player_name" : "Álvaro Arbeloa Coca",
    "player_nickname" : "Álvaro Arbeloa",
    "jersey_number" : 17,
    "country" : {
      "id" : 214,
      "name" : "Spain"
    },
    "cards" : [ ],
    "positions" : [ ]
  } ]
}, {
  "team_id" : 214,
  "team_name" : "Espanyol",
  "lineup" : [ {
    "player_id" : 4741,
    "player_name" : "Juan Rafael Fuentes Hernández",
    "player_nickname" : "Juan Rafael Fuentes",
    "jersey_number" : 18,
    "country" : {
      "id" : 214,
      "name" : "Spain"
    },
    "cards" : [ ],
    "positions" : [ ]
  }, {
    "player_id" : 6612,
    "player_name" : "Rubén Duarte Sánchez",
    "player_nickname" : "Rubén Duarte",
    "jersey_number" : 3,
    "country" : {
      "id" : 214,
      "name" : "Spain"
    },
    "cards" : [ ],
    "positions" : [ {
      "position_id" : 6,
      "position" : "Left Back",
      "from" : "00:00",
      "to" : "17:07",
      "from_period" : 1,
      "to_period" : 1,
      "start_reason" : "Starting XI",
      "end_reason" : "Tactical Shift"
    }, {
      "position_id" : 5,
      "position" : "Left Center Back",
      "from" : "17:07",
      "to" : "46:17",
      "from_period" : 1,
      "to_period" : 2,
      "start_reason" : "Tactical Shift",
      "end_reason" : "Tactical Shift"
    }, {
      "position_id" : 6,
      "position" : "Left Back",
      "from" : "46:17",
      "to" : "48:10",
      "from_period" : 2,
      "to_period" : 2,
      "start_reason" : "Tactical Shift",
      "end_reason" : "Tactical Shift"
    }, {
      "position_id" : 5,
      "position" : "Left Center Back",
      "from" : "48:10",
      "to" : null,
      "from_period" : 2,
      "to_period" : null,
      "start_reason" : "Tactical Shift",
      "end_reason" : "Final Whistle"
    } ]
  }, {
    "player_id" : 6701,
    "player_name" : "Joan Jordán Moreno",
    "player_nickname" : "Joan Jordán",
    "jersey_number" : 19,
    "country" : {
      "id" : 214,
      "name" : "Spain"
    },
    "cards" : [ ],
    "positions" : [ {
      "position_id" : 9,
      "position" : "Right Defensive Midfield",
      "from" : "64:34",
      "to" : null,
      "from_period" : 2,
      "to_period" : null,
      "start_reason" : "Substitution - On (Tactical)",
      "end_reason" : "Final Whistle"
    } ]
  }, {
    "player_id" : 6709,
    "player_name" : "Anaitz Arbilla Zabala",
    "player_nickname" : "Anaitz Arbilla",
    "jersey_number" : 23,
    "country" : {
      "id" : 214,
      "name" : "Spain"
    },
    "cards" : [ ],
    "positions" : [ {
      "position_id" : 2,
      "position" : "Right Back",
      "from" : "00:00",
      "to" : "17:07",
      "from_period" : 1,
      "to_period" : 1,
      "start_reason" : "Starting XI",
      "end_reason" : "Tactical Shift"
    }, {
      "position_id" : 7,
      "position" : "Right Wing Back",
      "from" : "17:07",
      "to" : "45:51",
      "from_period" : 1,
      "to_period" : 2,
      "start_reason" : "Tactical Shift",
      "end_reason" : "Tactical Shift"
    }, {
      "position_id" : 2,
      "position" : "Right Back",
      "from" : "45:51",
      "to" : null,
      "from_period" : 2,
      "to_period" : null,
      "start_reason" : "Tactical Shift",
      "end_reason" : "Final Whistle"
    } ]
  }, {
    "player_id" : 6758,
    "player_name" : "Víctor Sánchez Mata",
    "player_nickname" : "Víctor Sánchez",
    "jersey_number" : 4,
    "country" : {
      "id" : 214,
      "name" : "Spain"
    },
    "cards" : [ ],
    "positions" : [ {
      "position_id" : 9,
      "position" : "Right Defensive Midfield",
      "from" : "00:00",
      "to" : "17:07",
      "from_period" : 1,
      "to_period" : 1,
      "start_reason" : "Starting XI",
      "end_reason" : "Tactical Shift"
    }, {
      "position_id" : 15,
      "position" : "Left Center Midfield",
      "from" : "17:07",
      "to" : "45:51",
      "from_period" : 1,
      "to_period" : 2,
      "start_reason" : "Tactical Shift",
      "end_reason" : "Tactical Shift"
    }, {
      "position_id" : 9,
      "position" : "Right Defensive Midfield",
      "from" : "45:51",
      "to" : "64:34",
      "from_period" : 2,
      "to_period" : 2,
      "start_reason" : "Tactical Shift",
      "end_reason" : "Substitution - Off (Tactical)"
    } ]
  }, {
    "player_id" : 6762,
    "player_name" : "Álvaro González Soberón",
    "player_nickname" : "Álvaro González",
    "jersey_number" : 22,
    "country" : {
      "id" : 214,
      "name" : "Spain"
    },
    "cards" : [ {
      "time" : "15:34",
      "card_type" : "Yellow Card",
      "reason" : "Foul Committed",
      "period" : 1
    } ],
    "positions" : [ {
      "position_id" : 5,
      "position" : "Left Center Back",
      "from" : "00:00",
      "to" : "17:07",
      "from_period" : 1,
      "to_period" : 1,
      "start_reason" : "Starting XI",
      "end_reason" : "Tactical Shift"
    }, {
      "position_id" : 4,
      "position" : "Center Back",
      "from" : "17:07",
      "to" : "45:51",
      "from_period" : 1,
      "to_period" : 2,
      "start_reason" : "Tactical Shift",
      "end_reason" : "Tactical Shift"
    }, {
      "position_id" : 3,
      "position" : "Right Center Back",
      "from" : "45:51",
      "to" : "46:17",
      "from_period" : 2,
      "to_period" : 2,
      "start_reason" : "Tactical Shift",
      "end_reason" : "Tactical Shift"
    }, {
      "position_id" : 5,
      "position" : "Left Center Back",
      "from" : "46:17",
      "to" : "48:10",
      "from_period" : 2,
      "to_period" : 2,
      "start_reason" : "Tactical Shift",
      "end_reason" : "Tactical Shift"
    }, {
      "position_id" : 3,
      "position" : "Right Center Back",
      "from" : "48:10",
      "to" : null,
      "from_period" : 2,
      "to_period" : null,
      "start_reason" : "Tactical Shift",
      "end_reason" : "Final Whistle"
    } ]
  }, {
    "player_id" : 6766,
    "player_name" : "Gerard Moreno Balaguero",
    "player_nickname" : "Gerard Moreno",
    "jersey_number" : 7,
    "country" : {
      "id" : 214,
      "name" : "Spain"
    },
    "cards" : [ ],
    "positions" : [ {
      "position_id" : 24,
      "position" : "Left Center Forward",
      "from" : "00:00",
      "to" : "84:11",
      "from_period" : 1,
      "to_period" : 2,
      "start_reason" : "Starting XI",
      "end_reason" : "Tactical Shift"
    }, {
      "position_id" : 12,
      "position" : "Right Midfield",
      "from" : "84:11",
      "to" : null,
      "from_period" : 2,
      "to_period" : null,
      "start_reason" : "Tactical Shift",
      "end_reason" : "Final Whistle"
    } ]
  }, {
    "player_id" : 6791,
    "player_name" : "Javier López Rodríguez",
    "player_nickname" : "Javi López",
    "jersey_number" : 16,
    "country" : {
      "id" : 214,
      "name" : "Spain"
    },
    "cards" : [ ],
    "positions" : [ {
      "position_id" : 11,
      "position" : "Left Defensive Midfield",
      "from" : "00:00",
      "to" : "17:07",
      "from_period" : 1,
      "to_period" : 1,
      "start_reason" : "Starting XI",
      "end_reason" : "Tactical Shift"
    }, {
      "position_id" : 10,
      "position" : "Center Defensive Midfield",
      "from" : "17:07",
      "to" : "45:00",
      "from_period" : 1,
      "to_period" : 2,
      "start_reason" : "Tactical Shift",
      "end_reason" : "Substitution - Off (Tactical)"
    } ]
  }, {
    "player_id" : 6792,
    "player_name" : "Pau López Sabata",
    "player_nickname" : "Pau López",
    "jersey_number" : 13,
    "country" : {
      "id" : 214,
      "name" : "Spain"
    },
    "cards" : [ ],
    "positions" : [ {
      "position_id" : 1,
      "position" : "Goalkeeper",
      "from" : "00:00",
      "to" : null,
      "from_period" : 1,
      "to_period" : null,
      "start_reason" : "Starting XI",
      "end_reason" : "Final Whistle"
    } ]
  }, {
    "player_id" : 7781,
    "player_name" : "Felipe Salvador Caicedo Corozo",
    "player_nickname" : "Felipe Caicedo",
    "jersey_number" : 20,
    "country" : {
      "id" : 65,
      "name" : "Ecuador"
    },
    "cards" : [ ],
    "positions" : [ {
      "position_id" : 22,
      "position" : "Right Center Forward",
      "from" : "00:00",
      "to" : null,
      "from_period" : 1,
      "to_period" : null,
      "start_reason" : "Starting XI",
      "end_reason" : "Final Whistle"
    } ]
  }, {
    "player_id" : 13614,
    "player_name" : "Francesco Bardi",
    "player_nickname" : null,
    "jersey_number" : 1,
    "country" : {
      "id" : 112,
      "name" : "Italy"
    },
    "cards" : [ ],
    "positions" : [ ]
  }, {
    "player_id" : 15297,
    "player_name" : "Mickaël Ciani",
    "player_nickname" : null,
    "jersey_number" : 15,
    "country" : {
      "id" : 78,
      "name" : "France"
    },
    "cards" : [ ],
    "positions" : [ {
      "position_id" : 3,
      "position" : "Right Center Back",
      "from" : "00:00",
      "to" : "45:00",
      "from_period" : 1,
      "to_period" : 2,
      "start_reason" : "Starting XI",
      "end_reason" : "Substitution - Off (Tactical)"
    } ]
  }, {
    "player_id" : 18407,
    "player_name" : "José Alberto Cañas Ruiz Herrera",
    "player_nickname" : "José Alberto Cañas",
    "jersey_number" : 14,
    "country" : {
      "id" : 214,
      "name" : "Spain"
    },
    "cards" : [ {
      "time" : "65:41",
      "card_type" : "Yellow Card",
      "reason" : "Foul Committed",
      "period" : 2
    } ],
    "positions" : [ {
      "position_id" : 10,
      "position" : "Center Defensive Midfield",
      "from" : "45:00",
      "to" : "45:51",
      "from_period" : 2,
      "to_period" : 2,
      "start_reason" : "Substitution - On (Tactical)",
      "end_reason" : "Tactical Shift"
    }, {
      "position_id" : 11,
      "position" : "Left Defensive Midfield",
      "from" : "45:51",
      "to" : null,
      "from_period" : 2,
      "to_period" : null,
      "start_reason" : "Tactical Shift",
      "end_reason" : "Final Whistle"
    } ]
  }, {
    "player_id" : 23924,
    "player_name" : "Mamadou Sylla Diallo",
    "player_nickname" : "Mamadou Sylla",
    "jersey_number" : 28,
    "country" : {
      "id" : 202,
      "name" : "Senegal"
    },
    "cards" : [ ],
    "positions" : [ ]
  }, {
    "player_id" : 24072,
    "player_name" : "Salvador Sevilla López",
    "player_nickname" : "Salva Sevilla",
    "jersey_number" : 8,
    "country" : {
      "id" : 214,
      "name" : "Spain"
    },
    "cards" : [ ],
    "positions" : [ {
      "position_id" : 12,
      "position" : "Right Midfield",
      "from" : "00:00",
      "to" : "17:07",
      "from_period" : 1,
      "to_period" : 1,
      "start_reason" : "Starting XI",
      "end_reason" : "Tactical Shift"
    }, {
      "position_id" : 13,
      "position" : "Right Center Midfield",
      "from" : "17:07",
      "to" : "45:51",
      "from_period" : 1,
      "to_period" : 2,
      "start_reason" : "Tactical Shift",
      "end_reason" : "Tactical Shift"
    }, {
      "position_id" : 16,
      "position" : "Left Midfield",
      "from" : "45:51",
      "to" : "46:17",
      "from_period" : 2,
      "to_period" : 2,
      "start_reason" : "Tactical Shift",
      "end_reason" : "Tactical Shift"
    }, {
      "position_id" : 12,
      "position" : "Right Midfield",
      "from" : "46:17",
      "to" : "48:10",
      "from_period" : 2,
      "to_period" : 2,
      "start_reason" : "Tactical Shift",
      "end_reason" : "Tactical Shift"
    }, {
      "position_id" : 16,
      "position" : "Left Midfield",
      "from" : "48:10",
      "to" : null,
      "from_period" : 2,
      "to_period" : null,
      "start_reason" : "Tactical Shift",
      "end_reason" : "Final Whistle"
    } ]
  }, {
    "player_id" : 24086,
    "player_name" : "Antonio José Raillo Arenas",
    "player_nickname" : "Antonio Raillo",
    "jersey_number" : 24,
    "country" : {
      "id" : 214,
      "name" : "Spain"
    },
    "cards" : [ ],
    "positions" : [ ]
  }, {
    "player_id" : 24578,
    "player_name" : "Francisco Montañés Claverías",
    "player_nickname" : "Paco Montañés",
    "jersey_number" : 11,
    "country" : {
      "id" : 214,
      "name" : "Spain"
    },
    "cards" : [ ],
    "positions" : [ {
      "position_id" : 3,
      "position" : "Right Center Back",
      "from" : "45:00",
      "to" : "45:51",
      "from_period" : 2,
      "to_period" : 2,
      "start_reason" : "Substitution - On (Tactical)",
      "end_reason" : "Tactical Shift"
    }, {
      "position_id" : 12,
      "position" : "Right Midfield",
      "from" : "45:51",
      "to" : "46:17",
      "from_period" : 2,
      "to_period" : 2,
      "start_reason" : "Tactical Shift",
      "end_reason" : "Tactical Shift"
    }, {
      "position_id" : 16,
      "position" : "Left Midfield",
      "from" : "46:17",
      "to" : "48:10",
      "from_period" : 2,
      "to_period" : 2,
      "start_reason" : "Tactical Shift",
      "end_reason" : "Tactical Shift"
    }, {
      "position_id" : 12,
      "position" : "Right Midfield",
      "from" : "48:10",
      "to" : "84:11",
      "from_period" : 2,
      "to_period" : 2,
      "start_reason" : "Tactical Shift",
      "end_reason" : "Tactical Shift"
    }, {
      "position_id" : 24,
      "position" : "Left Center Forward",
      "from" : "84:11",
      "to" : null,
      "from_period" : 2,
      "to_period" : null,
      "start_reason" : "Tactical Shift",
      "end_reason" : "Final Whistle"
    } ]
  }, {
    "player_id" : 27241,
    "player_name" : "Víctor Guillermo Álvarez Delgado",
    "player_nickname" : "Víctor Álvarez",
    "jersey_number" : 5,
    "country" : {
      "id" : 214,
      "name" : "Spain"
    },
    "cards" : [ ],
    "positions" : [ {
      "position_id" : 16,
      "position" : "Left Midfield",
      "from" : "00:00",
      "to" : "17:07",
      "from_period" : 1,
      "to_period" : 1,
      "start_reason" : "Starting XI",
      "end_reason" : "Tactical Shift"
    }, {
      "position_id" : 8,
      "position" : "Left Wing Back",
      "from" : "17:07",
      "to" : "45:51",
      "from_period" : 1,
      "to_period" : 2,
      "start_reason" : "Tactical Shift",
      "end_reason" : "Tactical Shift"
    }, {
      "position_id" : 6,
      "position" : "Left Back",
      "from" : "45:51",
      "to" : "46:17",
      "from_period" : 2,
      "to_period" : 2,
      "start_reason" : "Tactical Shift",
      "end_reason" : "Tactical Shift"
    }, {
      "position_id" : 3,
      "position" : "Right Center Back",
      "from" : "46:17",
      "to" : "48:10",
      "from_period" : 2,
      "to_period" : 2,
      "start_reason" : "Tactical Shift",
      "end_reason" : "Tactical Shift"
    }, {
      "position_id" : 6,
      "position" : "Left Back",
      "from" : "48:10",
      "to" : null,
      "from_period" : 2,
      "to_period" : null,
      "start_reason" : "Tactical Shift",
      "end_reason" : "Final Whistle"
    } ]
  } ]
} ]